{"stats":{"minecraft:used":{"minecraft:water_bucket":1,"minecraft:dark_oak_leaves":1,"minecraft:brown_mushroom_block":1,"minecraft:splash_potion":161,"minecraft:stripped_spruce_log":9},"minecraft:mined":{"minecraft:fire":44,"minecraft:oak_leaves":4,"minecraft:dark_oak_leaves":1},"minecraft:picked_up":{"minecraft:oak_sapling":1},"minecraft:custom":{"minecraft:jump":60,"minecraft:time_since_rest":255,"minecraft:damage_taken":230,"minecraft:crouch_one_cm":188,"minecraft:leave_game":7,"minecraft:sprint_one_cm":7671,"minecraft:play_time":8452,"minecraft:walk_one_cm":6785,"minecraft:time_since_death":235,"minecraft:deaths":2,"minecraft:sneak_time":519,"minecraft:total_world_time":8452,"minecraft:walk_under_water_one_cm":1661,"minecraft:fly_one_cm":89543,"minecraft:fall_one_cm":2930}},"DataVersion":3337}